totemp/__init__.py
totemp/temperature_types.py
totemp-0.5.1.dist-info/LICENSE
totemp-0.5.1.dist-info/METADATA
totemp-0.5.1.dist-info/WHEEL
totemp-0.5.1.dist-info/RECORD
