Metadata-Version: 2.1
Name: totemp
Version: 0.5.1
Summary: Temperature Converter
Home-page: https://github.com/eddyyxxyy/ToTemp
License: GPL-3.0-only
Keywords: converter,temperature,celsius,kelvin,fahrenheit,rankine,delisle,Newton,Réaumur,Rømer
Author: Edson Pimenta
Author-email: edson.tibo@gmail.com
Maintainer: Edson Pimenta
Maintainer-email: edson.tibo@gmail.com
Requires-Python: >=3.10,<4.0
Classifier: Intended Audience :: Developers
Classifier: Intended Audience :: Science/Research
Classifier: License :: OSI Approved :: GNU Affero General Public License v3
Classifier: License :: OSI Approved :: GNU General Public License v3 (GPLv3)
Classifier: Operating System :: OS Independent
Classifier: Programming Language :: Python :: 3
Classifier: Programming Language :: Python :: 3.10
Classifier: Programming Language :: Python :: 3.11
Classifier: Topic :: Scientific/Engineering :: Mathematics
Classifier: Topic :: Software Development :: Libraries
Classifier: Topic :: Software Development :: Libraries :: Python Modules
Project-URL: Documentation, https://totemp.readthedocs.io/en/latest/
